demand/__init__.py
demand_emergence.studio-0.0.1.dist-info/LICENSE
demand_emergence.studio-0.0.1.dist-info/METADATA
demand_emergence.studio-0.0.1.dist-info/WHEEL
demand_emergence.studio-0.0.1.dist-info/top_level.txt
demand_emergence.studio-0.0.1.dist-info/RECORD
