Metadata-Version: 2.1
Name: demand-emergence.studio
Version: 0.0.1
Summary: An all encompassing suite for demand forecasting.
Home-page: https://github.com/jamesonl/demand
Author: Jameson Lee
Author-email: jameson.lee@emergence.studio
License: UNKNOWN
Platform: UNKNOWN
Classifier: Programming Language :: Python :: 3
Classifier: License :: OSI Approved :: MIT License
Classifier: Operating System :: OS Independent
Requires-Python: >=3.8.2
